<?xml version="1.0" encoding="UTF-8" ?><adfc-config xmlns="http://xmlns.oracle.com/adf/controller" version="1.2">  <task-flow-definition id="informacion-task-flow">    <template-reference>      <document>/WEB-INF/plantilla/maestro-template.xml</document>      <id>maestro-template</id>    </template-reference>    <managed-bean id="__1">      <managed-bean-name>PPRBackingErrorRest</managed-bean-name>      <managed-bean-class>viewManifiesto.errorRest.PPRListaFrg</managed-bean-class>      <managed-bean-scope>request</managed-bean-scope>    </managed-bean>    <managed-bean id="__2">      <managed-bean-name>PPRBackingPreliquidacionItemFrg</managed-bean-name>      <managed-bean-class>viewManifiesto.preliquidacion.PPRItemFrg</managed-bean-class>      <managed-bean-scope>request</managed-bean-scope>    </managed-bean>    <view id="ListaFrg">      <page>/informacion/ListaFrg.jsff</page>    </view>    <view id="ItemFrg">      <page>/informacion/ItemFrg.jsff</page>    </view>    <use-page-fragments/>  </task-flow-definition></adfc-config>