<?xml version="1.0" encoding="UTF-8" ?><!DOCTYPE ViewObject SYSTEM "jbo_03_01.dtd"><!----><ViewObject  xmlns="http://xmlns.oracle.com/bc4j"  Name="UsuarioAsignadoViewNoDML"  Version="12.2.1.22.48"  InheritPersonalization="merge"  BindingStyle="JDBC"  CustomQuery="true"  ComponentClass="modelManifiesto.bc.vistaNoDML.UsuarioAsignadoViewNoDMLImpl"  FetchMode="FETCH_AS_NEEDED"  PageIterMode="Full"  MaxFetchSize="50"  AccessMode="DEFAULT"  ComponentInterface="modelManifiesto.bc.vistaNoDML.common.UsuarioAsignadoViewNoDML">  <DesignTime>    <Attr Name="_isExpertMode" Value="true"/>    <Attr Name="_codeGenFlag2" Value="Coll"/>  </DesignTime>  <Properties>    <SchemaBasedProperties>      <LABEL        ResId="modelManifiesto.bc.vistaNoDML.UsuarioAsignadoViewNoDML_LABEL"/>    </SchemaBasedProperties>  </Properties>  <Variable    Name="v_Nick"    Kind="viewcriteria"    Type="java.lang.String"/>  <Variable    Name="v_Nombre"    Kind="viewcriteria"    Type="java.lang.String"/>  <Variable    Name="v_Apellido"    Kind="viewcriteria"    Type="java.lang.String"/>  <Variable    Name="v_IdUsuario"    Kind="viewcriteria"    Type="java.lang.Integer"/>  <SQLQuery><![CDATA[select	u.id_usuario,	u.nick,	u.nombre,	u.apellido,	au.id_libro_direccion_aerolinea,	case		when au.id_libro_direccion_aerolinea is not null then 	(		select			nombre		from			MV_001_00.libro_direccion ld		where			ld.indice = au.id_libro_direccion_aerolinea		)		else null	end as nombre_aerolineafrom	GS_001_00.usuario uleft join MV_001_00.aerolinea_usuario auon	u.id_usuario = au.id_usuarioorder by u.nick]]></SQLQuery>  <ViewAttribute    Name="IdUsuario"    IsUpdateable="false"    IsPersistent="false"    PrecisionRule="true"    Type="java.lang.Integer"    ColumnType="INTEGER"    AliasName="id_usuario"    Expression="id_usuario"    SQLType="INTEGER"    Domain="model.bc.dominio.IdEntidad">    <DesignTime>      <Attr Name="_DisplaySize" Value="11"/>    </DesignTime>    <Properties>      <SchemaBasedProperties>        <LABEL          ResId="modelManifiesto.bc.vistaNoDML.UsuarioAsignadoViewNoDML.IdUsuario_LABEL"/>      </SchemaBasedProperties>    </Properties>  </ViewAttribute>  <ViewAttribute    Name="Nick"    IsUpdateable="false"    IsPersistent="false"    PrecisionRule="true"    Precision="128"    Type="java.lang.String"    ColumnType="VARCHAR"    AliasName="nick"    Expression="nick"    SQLType="VARCHAR"    Domain="model.bc.dominio.Texto">    <DesignTime>      <Attr Name="_DisplaySize" Value="128"/>    </DesignTime>    <Properties>      <SchemaBasedProperties>        <LABEL          ResId="modelManifiesto.bc.vistaNoDML.UsuarioAsignadoViewNoDML.Nick_LABEL"/>      </SchemaBasedProperties>    </Properties>  </ViewAttribute>  <ViewAttribute    Name="Nombre"    IsUpdateable="false"    IsPersistent="false"    PrecisionRule="true"    Precision="128"    Type="java.lang.String"    ColumnType="VARCHAR"    AliasName="nombre"    Expression="nombre"    SQLType="VARCHAR"    Domain="model.bc.dominio.Texto">    <DesignTime>      <Attr Name="_DisplaySize" Value="128"/>    </DesignTime>  </ViewAttribute>  <ViewAttribute    Name="Apellido"    IsUpdateable="false"    IsPersistent="false"    PrecisionRule="true"    Precision="128"    Type="java.lang.String"    ColumnType="VARCHAR"    AliasName="apellido"    Expression="apellido"    SQLType="VARCHAR"    Domain="model.bc.dominio.Texto">    <DesignTime>      <Attr Name="_DisplaySize" Value="128"/>    </DesignTime>  </ViewAttribute>  <ViewAttribute    Name="IdLibroDireccionAerolinea"    IsUpdateable="false"    IsPersistent="false"    PrecisionRule="true"    Type="java.lang.Integer"    ColumnType="INT"    AliasName="id_libro_direccion_aerolinea"    Expression="id_libro_direccion_aerolinea"    SQLType="INTEGER"    Domain="model.bc.dominio.ComboBox">    <DesignTime>      <Attr Name="_DisplaySize" Value="11"/>    </DesignTime>  </ViewAttribute>  <ViewAttribute    Name="NombreAerolinea"    IsUpdateable="false"    IsPersistent="false"    PrecisionRule="true"    Precision="128"    Type="java.lang.String"    ColumnType="VARCHAR"    AliasName="nombre_aerolinea"    Expression="nombre_aerolinea"    SQLType="VARCHAR"    Domain="model.bc.dominio.Texto">    <DesignTime>      <Attr Name="_DisplaySize" Value="128"/>    </DesignTime>    <Properties>      <SchemaBasedProperties>        <LABEL          ResId="modelManifiesto.bc.vistaNoDML.UsuarioAsignadoViewNoDML.NombreAerolinea_LABEL"/>      </SchemaBasedProperties>    </Properties>  </ViewAttribute>  <ViewCriteria    Name="UsuarioAsignadoViewNoDMLCriteria"    ViewObjectName="modelManifiesto.bc.vistaNoDML.UsuarioAsignadoViewNoDML"    Conjunction="AND">    <Properties Name="_Props">      <CustomProperties>        <Property          Name="autoExecute"          Value="false"/>        <Property          Name="mode"          Value="Basic"/>        <Property          Name="allowConjunctionOverride"          Value="true"/>        <Property          Name="showInList"          Value="true"/>        <Property          Name="displayOperators"          Value="InAdvancedMode"/>      </CustomProperties>    </Properties>    <ViewCriteriaRow      Name="UsuarioAsignadoViewNoDMLCriteria_row_0"      UpperColumns="1">      <ViewCriteriaItem        Name="Nick"        ViewAttribute="Nick"        Operator="CONTAINS"        Conjunction="AND"        Value=":v_Nick"        IsBindVarValue="true"        Required="SelectivelyRequired"        ValidateBindVars="true"/>      <ViewCriteriaItem        Name="Nombre"        ViewAttribute="Nombre"        Operator="CONTAINS"        Conjunction="AND"        Value=":v_Nombre"        IsBindVarValue="true"        Required="SelectivelyRequired"        ValidateBindVars="true"/>      <ViewCriteriaItem        Name="UsuarioAsignadoViewNoDMLCriteria_UsuarioAsignadoViewNoDMLCriteria_row_0_Apellido"        ViewAttribute="Apellido"        Operator="CONTAINS"        Conjunction="AND"        Value=":v_Apellido"        IsBindVarValue="true"        Required="SelectivelyRequired"        ValidateBindVars="true"/>    </ViewCriteriaRow>  </ViewCriteria>  <ViewCriteria    Name="UsuarioAsignadoViewNoDMLCriteriaByIdUsuario"    ViewObjectName="modelManifiesto.bc.vistaNoDML.UsuarioAsignadoViewNoDML"    Conjunction="AND">    <Properties Name="_Props">      <CustomProperties>        <Property          Name="autoExecute"          Value="false"/>        <Property          Name="mode"          Value="Basic"/>        <Property          Name="allowConjunctionOverride"          Value="true"/>        <Property          Name="showInList"          Value="true"/>        <Property          Name="displayOperators"          Value="InAdvancedMode"/>      </CustomProperties>    </Properties>    <ViewCriteriaRow      Name="UsuarioAsignadoViewNoDMLCriteria1_row_0"      UpperColumns="1">      <ViewCriteriaItem        Name="IdUsuario"        ViewAttribute="IdUsuario"        Operator="="        Conjunction="AND"        Value=":v_IdUsuario"        IsBindVarValue="true"        Required="Optional"/>    </ViewCriteriaRow>  </ViewCriteria>  <AttrArray Name="KeyAttributes">    <Item Value="IdUsuario"/>  </AttrArray>  <ClientInterface    Name="__clientInterface">    <Method      Name="ejecutarByIndice"      MethodName="ejecutarByIndice">      <Return        Name="_return_type_"        Type="void"/>      <Parameter        Name="idUsuario"        Type="int"/>    </Method>  </ClientInterface>  <ResourceBundle>    <PropertiesBundle      PropertiesFile="modelManifiesto.ModelManifiestoBundle"/>  </ResourceBundle></ViewObject>